plotman/__init__.py
plotman/__main__.py
plotman/analyzer.py
plotman/archive.py
plotman/chiapos.py
plotman/configuration.py
plotman/csv_exporter.py
plotman/errors.py
plotman/interactive.py
plotman/job.py
plotman/manager.py
plotman/plot_util.py
plotman/plotman.py
plotman/reporting.py
plotman/_tests/__init__.py
plotman/_tests/archive_test.py
plotman/_tests/configuration_test.py
plotman/_tests/manager_test.py
plotman/_tests/plot_util_test.py
plotman/_tests/reporting_test.py
plotman/_tests/plotters/__init__.py
plotman/_tests/plotters/test_bladebit.py
plotman/_tests/plotters/test_chianetwork.py
plotman/_tests/plotters/test_core.py
plotman/_tests/plotters/test_init.py
plotman/_tests/plotters/test_madmax.py
plotman/_tests/resources/__init__.py
plotman/_tests/resources/bladebit.marked
plotman/_tests/resources/bladebit.plot.log
plotman/_tests/resources/chianetwork.marked
plotman/_tests/resources/chianetwork.notes
plotman/_tests/resources/chianetwork.plot.log
plotman/_tests/resources/madmax.marked
plotman/_tests/resources/madmax.notes
plotman/_tests/resources/madmax.plot.log
plotman/plotters/__init__.py
plotman/plotters/bladebit.py
plotman/plotters/chianetwork.py
plotman/plotters/core.py
plotman/plotters/madmax.py
plotman/resources/__init__.py
plotman/resources/plotman.yaml
plotman/resources/target_definitions.yaml
plotman-0.5.3.data/data/bin/listlogs
plotman-0.5.3.data/data/config/plotman.yaml
plotman-0.5.3.dist-info/LICENSE
plotman-0.5.3.dist-info/METADATA
plotman-0.5.3.dist-info/WHEEL
plotman-0.5.3.dist-info/entry_points.txt
plotman-0.5.3.dist-info/top_level.txt
plotman-0.5.3.dist-info/RECORD
