Metadata-Version: 2.1
Name: plotman
Version: 0.5.3
Summary: Chia plotting manager
Home-page: https://github.com/ericaltendorf/plotman
Author: Eric Altendorf
License: Apache 2.0
Project-URL: Bug Tracker, https://github.com/ericaltendorf/plotman/issues
Project-URL: Changelog, https://github.com/ericaltendorf/plotman/blob/main/CHANGELOG.md
Keywords: chia,blockchain,automation,process management
Platform: UNKNOWN
Classifier: Development Status :: 3 - Alpha
Classifier: Environment :: Console :: Curses
Classifier: Intended Audience :: Developers
Classifier: Intended Audience :: System Administrators
Classifier: Intended Audience :: Information Technology
Classifier: License :: OSI Approved :: Apache Software License
Classifier: Natural Language :: English
Classifier: Operating System :: POSIX :: Linux
Classifier: Operating System :: MacOS :: MacOS X
Classifier: Programming Language :: Python :: 3
Classifier: Programming Language :: Python :: Implementation :: CPython
Classifier: Programming Language :: Python :: Implementation :: PyPy
Classifier: Topic :: System :: Monitoring
Classifier: Topic :: System :: Systems Administration
Classifier: Topic :: Utilities
License-File: LICENSE
Requires-Dist: appdirs (~=1.4)
Requires-Dist: attrs (==21.2)
Requires-Dist: click (~=7.1)
Requires-Dist: desert (==2020.11.18)
Requires-Dist: marshmallow (~=3.12)
Requires-Dist: packaging (~=20.9)
Requires-Dist: pendulum (~=2.1)
Requires-Dist: psutil (~=5.8)
Requires-Dist: pyyaml (~=5.4)
Requires-Dist: texttable (~=1.6)
Requires-Dist: typing-extensions (~=3.10)
Provides-Extra: checks
Requires-Dist: black (==21.7b0) ; extra == 'checks'
Requires-Dist: check-manifest (~=0.46) ; extra == 'checks'
Requires-Dist: mypy (==0.902) ; extra == 'checks'
Requires-Dist: types-pkg-resources (~=0.1.2) ; extra == 'checks'
Requires-Dist: coverage ; extra == 'checks'
Requires-Dist: diff-cover ; extra == 'checks'
Requires-Dist: pytest ; extra == 'checks'
Requires-Dist: pytest-cov ; extra == 'checks'
Requires-Dist: pyfakefs ; extra == 'checks'
Provides-Extra: coverage
Requires-Dist: coverage ; extra == 'coverage'
Requires-Dist: diff-cover ; extra == 'coverage'
Provides-Extra: dev
Requires-Dist: coverage ; extra == 'dev'
Requires-Dist: diff-cover ; extra == 'dev'
Requires-Dist: pytest ; extra == 'dev'
Requires-Dist: pytest-cov ; extra == 'dev'
Requires-Dist: pyfakefs ; extra == 'dev'
Requires-Dist: isort ; extra == 'dev'
Provides-Extra: test
Requires-Dist: coverage ; extra == 'test'
Requires-Dist: diff-cover ; extra == 'test'
Requires-Dist: pytest ; extra == 'test'
Requires-Dist: pytest-cov ; extra == 'test'
Requires-Dist: pyfakefs ; extra == 'test'
